open_FRED/__init__.py
open_FRED/__main__.py
open_FRED/cli.py
open_FRED/netcdftools/add_dimension.py
open_FRED/netcdftools/minmax.py
open_FRED/netcdftools/monthly.py
open_FRED_cli-0.0.1.dist-info/AUTHORS.rst
open_FRED_cli-0.0.1.dist-info/LICENSE
open_FRED_cli-0.0.1.dist-info/METADATA
open_FRED_cli-0.0.1.dist-info/WHEEL
open_FRED_cli-0.0.1.dist-info/entry_points.txt
open_FRED_cli-0.0.1.dist-info/top_level.txt
open_FRED_cli-0.0.1.dist-info/RECORD
